[
  {
    "Question ID": "FW-Y1-L08-Q001",
    "Status": "Approved",
    "Review Status": "Approved",
    "Subject": "Mathematics",
    "Year": "Year 1",
    "World": "Forest World",
    "Level": "Level 08",
    "Topic": "Review",
    "Subtopic": "Counting review",
    "Learning Objective": "Review counting objects up to 10.",
    "Difficulty": "Easy",
    "Question Type": "Multiple Choice",
    "Question": "Count the apples. How many apples are there?",
    "Visual Object": "apple",
    "Visual Description": "Show exactly 2 apples in a clear forest scene.",
    "Options": "1|2|3",
    "Correct Answer": "2",
    "Step 1": "Look at the objects.",
    "Step 2": "Count each apple one by one.",
    "Step 3": "The total is 2.",
    "Final Explanation": "The correct answer is 2.",
    "LearnBot Tip": "Point to each apple once as you count.",
    "Assessment Eligible": "Yes",
    "Curriculum Alignment": "Both",
    "Estimated Time": "25",
    "Voice Script": "Let's solve it together. Look at the objects. Count each apple one by one. The total is 2.",
    "Teaching Notes": "Review counting objects up to 10. | Look at the objects. | Count each apple one by one. | The total is 2. | Point to each apple once as you count.",
    "Required Assets": "visual:apple|type:Multiple Choice",
    "Version Notes": "v1.0 - Mathematics Year 1 Forest complete"
  },
  {
    "Question ID": "FW-Y1-L08-Q002",
    "Status": "Approved",
    "Review Status": "Approved",
    "Subject": "Mathematics",
    "Year": "Year 1",
    "World": "Forest World",
    "Level": "Level 08",
    "Topic": "Review",
    "Subtopic": "Counting review",
    "Learning Objective": "Review counting objects up to 10.",
    "Difficulty": "Easy",
    "Question Type": "Multiple Choice",
    "Question": "Count the stars. How many stars are there?",
    "Visual Object": "star",
    "Visual Description": "Show exactly 3 stars in a clear forest scene.",
    "Options": "2|3|4",
    "Correct Answer": "3",
    "Step 1": "Look at the objects.",
    "Step 2": "Count each star one by one.",
    "Step 3": "The total is 3.",
    "Final Explanation": "The correct answer is 3.",
    "LearnBot Tip": "Point to each star once as you count.",
    "Assessment Eligible": "Yes",
    "Curriculum Alignment": "Both",
    "Estimated Time": "25",
    "Voice Script": "Let's solve it together. Look at the objects. Count each star one by one. The total is 3.",
    "Teaching Notes": "Review counting objects up to 10. | Look at the objects. | Count each star one by one. | The total is 3. | Point to each star once as you count.",
    "Required Assets": "visual:star|type:Multiple Choice",
    "Version Notes": "v1.0 - Mathematics Year 1 Forest complete"
  },
  {
    "Question ID": "FW-Y1-L08-Q003",
    "Status": "Approved",
    "Review Status": "Approved",
    "Subject": "Mathematics",
    "Year": "Year 1",
    "World": "Forest World",
    "Level": "Level 08",
    "Topic": "Review",
    "Subtopic": "Counting review",
    "Learning Objective": "Review counting objects up to 10.",
    "Difficulty": "Easy",
    "Question Type": "Multiple Choice",
    "Question": "Count the ducks. How many ducks are there?",
    "Visual Object": "duck",
    "Visual Description": "Show exactly 4 ducks in a clear forest scene.",
    "Options": "3|4|5",
    "Correct Answer": "4",
    "Step 1": "Look at the objects.",
    "Step 2": "Count each duck one by one.",
    "Step 3": "The total is 4.",
    "Final Explanation": "The correct answer is 4.",
    "LearnBot Tip": "Point to each duck once as you count.",
    "Assessment Eligible": "Yes",
    "Curriculum Alignment": "Both",
    "Estimated Time": "25",
    "Voice Script": "Let's solve it together. Look at the objects. Count each duck one by one. The total is 4.",
    "Teaching Notes": "Review counting objects up to 10. | Look at the objects. | Count each duck one by one. | The total is 4. | Point to each duck once as you count.",
    "Required Assets": "visual:duck|type:Multiple Choice",
    "Version Notes": "v1.0 - Mathematics Year 1 Forest complete"
  },
  {
    "Question ID": "FW-Y1-L08-Q004",
    "Status": "Approved",
    "Review Status": "Approved",
    "Subject": "Mathematics",
    "Year": "Year 1",
    "World": "Forest World",
    "Level": "Level 08",
    "Topic": "Review",
    "Subtopic": "Counting review",
    "Learning Objective": "Review counting objects up to 10.",
    "Difficulty": "Easy",
    "Question Type": "Multiple Choice",
    "Question": "Count the balls. How many balls are there?",
    "Visual Object": "ball",
    "Visual Description": "Show exactly 5 balls in a clear forest scene.",
    "Options": "4|5|6",
    "Correct Answer": "5",
    "Step 1": "Look at the objects.",
    "Step 2": "Count each ball one by one.",
    "Step 3": "The total is 5.",
    "Final Explanation": "The correct answer is 5.",
    "LearnBot Tip": "Point to each ball once as you count.",
    "Assessment Eligible": "Yes",
    "Curriculum Alignment": "Both",
    "Estimated Time": "25",
    "Voice Script": "Let's solve it together. Look at the objects. Count each ball one by one. The total is 5.",
    "Teaching Notes": "Review counting objects up to 10. | Look at the objects. | Count each ball one by one. | The total is 5. | Point to each ball once as you count.",
    "Required Assets": "visual:ball|type:Multiple Choice",
    "Version Notes": "v1.0 - Mathematics Year 1 Forest complete"
  },
  {
    "Question ID": "FW-Y1-L08-Q005",
    "Status": "Approved",
    "Review Status": "Approved",
    "Subject": "Mathematics",
    "Year": "Year 1",
    "World": "Forest World",
    "Level": "Level 08",
    "Topic": "Review",
    "Subtopic": "Counting review",
    "Learning Objective": "Review counting objects up to 10.",
    "Difficulty": "Easy",
    "Question Type": "Multiple Choice",
    "Question": "Count the flowers. How many flowers are there?",
    "Visual Object": "flower",
    "Visual Description": "Show exactly 6 flowers in a clear forest scene.",
    "Options": "5|6|7",
    "Correct Answer": "6",
    "Step 1": "Look at the objects.",
    "Step 2": "Count each flower one by one.",
    "Step 3": "The total is 6.",
    "Final Explanation": "The correct answer is 6.",
    "LearnBot Tip": "Point to each flower once as you count.",
    "Assessment Eligible": "Yes",
    "Curriculum Alignment": "Both",
    "Estimated Time": "25",
    "Voice Script": "Let's solve it together. Look at the objects. Count each flower one by one. The total is 6.",
    "Teaching Notes": "Review counting objects up to 10. | Look at the objects. | Count each flower one by one. | The total is 6. | Point to each flower once as you count.",
    "Required Assets": "visual:flower|type:Multiple Choice",
    "Version Notes": "v1.0 - Mathematics Year 1 Forest complete"
  },
  {
    "Question ID": "FW-Y1-L08-Q006",
    "Status": "Approved",
    "Review Status": "Approved",
    "Subject": "Mathematics",
    "Year": "Year 1",
    "World": "Forest World",
    "Level": "Level 08",
    "Topic": "Review",
    "Subtopic": "Counting review",
    "Learning Objective": "Review counting objects up to 10.",
    "Difficulty": "Medium",
    "Question Type": "Multiple Choice",
    "Question": "Count the oranges. How many oranges are there?",
    "Visual Object": "orange",
    "Visual Description": "Show exactly 7 oranges in a clear forest scene.",
    "Options": "6|7|8",
    "Correct Answer": "7",
    "Step 1": "Look at the objects.",
    "Step 2": "Count each orange one by one.",
    "Step 3": "The total is 7.",
    "Final Explanation": "The correct answer is 7.",
    "LearnBot Tip": "Point to each orange once as you count.",
    "Assessment Eligible": "Yes",
    "Curriculum Alignment": "Both",
    "Estimated Time": "25",
    "Voice Script": "Let's solve it together. Look at the objects. Count each orange one by one. The total is 7.",
    "Teaching Notes": "Review counting objects up to 10. | Look at the objects. | Count each orange one by one. | The total is 7. | Point to each orange once as you count.",
    "Required Assets": "visual:orange|type:Multiple Choice",
    "Version Notes": "v1.0 - Mathematics Year 1 Forest complete"
  },
  {
    "Question ID": "FW-Y1-L08-Q007",
    "Status": "Approved",
    "Review Status": "Approved",
    "Subject": "Mathematics",
    "Year": "Year 1",
    "World": "Forest World",
    "Level": "Level 08",
    "Topic": "Review",
    "Subtopic": "Counting review",
    "Learning Objective": "Review counting objects up to 10.",
    "Difficulty": "Medium",
    "Question Type": "Multiple Choice",
    "Question": "Count the fish. How many fish are there?",
    "Visual Object": "fish",
    "Visual Description": "Show exactly 8 fish in a clear forest scene.",
    "Options": "7|8|9",
    "Correct Answer": "8",
    "Step 1": "Look at the objects.",
    "Step 2": "Count each fish one by one.",
    "Step 3": "The total is 8.",
    "Final Explanation": "The correct answer is 8.",
    "LearnBot Tip": "Point to each fish once as you count.",
    "Assessment Eligible": "Yes",
    "Curriculum Alignment": "Both",
    "Estimated Time": "25",
    "Voice Script": "Let's solve it together. Look at the objects. Count each fish one by one. The total is 8.",
    "Teaching Notes": "Review counting objects up to 10. | Look at the objects. | Count each fish one by one. | The total is 8. | Point to each fish once as you count.",
    "Required Assets": "visual:fish|type:Multiple Choice",
    "Version Notes": "v1.0 - Mathematics Year 1 Forest complete"
  },
  {
    "Question ID": "FW-Y1-L08-Q008",
    "Status": "Approved",
    "Review Status": "Approved",
    "Subject": "Mathematics",
    "Year": "Year 1",
    "World": "Forest World",
    "Level": "Level 08",
    "Topic": "Review",
    "Subtopic": "Counting review",
    "Learning Objective": "Review counting objects up to 10.",
    "Difficulty": "Medium",
    "Question Type": "Multiple Choice",
    "Question": "Count the leaves. How many leaves are there?",
    "Visual Object": "leaf",
    "Visual Description": "Show exactly 9 leaves in a clear forest scene.",
    "Options": "8|9|10",
    "Correct Answer": "9",
    "Step 1": "Look at the objects.",
    "Step 2": "Count each leaf one by one.",
    "Step 3": "The total is 9.",
    "Final Explanation": "The correct answer is 9.",
    "LearnBot Tip": "Point to each leaf once as you count.",
    "Assessment Eligible": "Yes",
    "Curriculum Alignment": "Both",
    "Estimated Time": "25",
    "Voice Script": "Let's solve it together. Look at the objects. Count each leaf one by one. The total is 9.",
    "Teaching Notes": "Review counting objects up to 10. | Look at the objects. | Count each leaf one by one. | The total is 9. | Point to each leaf once as you count.",
    "Required Assets": "visual:leaf|type:Multiple Choice",
    "Version Notes": "v1.0 - Mathematics Year 1 Forest complete"
  },
  {
    "Question ID": "FW-Y1-L08-Q009",
    "Status": "Approved",
    "Review Status": "Approved",
    "Subject": "Mathematics",
    "Year": "Year 1",
    "World": "Forest World",
    "Level": "Level 08",
    "Topic": "Review",
    "Subtopic": "Addition review",
    "Learning Objective": "Review addition within 10.",
    "Difficulty": "Easy",
    "Question Type": "Multiple Choice",
    "Question": "1 apple plus 1 more apples. How many apples altogether?",
    "Visual Object": "apple",
    "Visual Description": "Show 1 apple + 1 apple = 2. Use a plus sign, never 'or'.",
    "Options": "1|2|3",
    "Correct Answer": "2",
    "Step 1": "Start with 1 apple.",
    "Step 2": "Add 1 more apples.",
    "Step 3": "Count all: 2.",
    "Final Explanation": "The correct answer is 2.",
    "LearnBot Tip": "Addition means putting groups together.",
    "Assessment Eligible": "Yes",
    "Curriculum Alignment": "Both",
    "Estimated Time": "35",
    "Voice Script": "Let's solve it together. Start with 1 apple. Add 1 more apples. Count all: 2.",
    "Teaching Notes": "Review addition within 10. | Start with 1 apple. | Add 1 more apples. | Count all: 2. | Addition means putting groups together.",
    "Required Assets": "visual:apple|type:Multiple Choice",
    "Version Notes": "v1.0 - Mathematics Year 1 Forest complete"
  },
  {
    "Question ID": "FW-Y1-L08-Q010",
    "Status": "Approved",
    "Review Status": "Approved",
    "Subject": "Mathematics",
    "Year": "Year 1",
    "World": "Forest World",
    "Level": "Level 08",
    "Topic": "Review",
    "Subtopic": "Addition review",
    "Learning Objective": "Review addition within 10.",
    "Difficulty": "Easy",
    "Question Type": "Multiple Choice",
    "Question": "2 stars plus 1 more stars. How many stars altogether?",
    "Visual Object": "star",
    "Visual Description": "Show 2 stars + 1 star = 3. Use a plus sign, never 'or'.",
    "Options": "2|3|4",
    "Correct Answer": "3",
    "Step 1": "Start with 2 stars.",
    "Step 2": "Add 1 more stars.",
    "Step 3": "Count all: 3.",
    "Final Explanation": "The correct answer is 3.",
    "LearnBot Tip": "Addition means putting groups together.",
    "Assessment Eligible": "Yes",
    "Curriculum Alignment": "Both",
    "Estimated Time": "35",
    "Voice Script": "Let's solve it together. Start with 2 stars. Add 1 more stars. Count all: 3.",
    "Teaching Notes": "Review addition within 10. | Start with 2 stars. | Add 1 more stars. | Count all: 3. | Addition means putting groups together.",
    "Required Assets": "visual:star|type:Multiple Choice",
    "Version Notes": "v1.0 - Mathematics Year 1 Forest complete"
  },
  {
    "Question ID": "FW-Y1-L08-Q011",
    "Status": "Approved",
    "Review Status": "Approved",
    "Subject": "Mathematics",
    "Year": "Year 1",
    "World": "Forest World",
    "Level": "Level 08",
    "Topic": "Review",
    "Subtopic": "Addition review",
    "Learning Objective": "Review addition within 10.",
    "Difficulty": "Easy",
    "Question Type": "Multiple Choice",
    "Question": "2 oranges plus 2 more oranges. How many oranges altogether?",
    "Visual Object": "orange",
    "Visual Description": "Show 2 oranges + 2 oranges = 4. Use a plus sign, never 'or'.",
    "Options": "3|4|5",
    "Correct Answer": "4",
    "Step 1": "Start with 2 oranges.",
    "Step 2": "Add 2 more oranges.",
    "Step 3": "Count all: 4.",
    "Final Explanation": "The correct answer is 4.",
    "LearnBot Tip": "Addition means putting groups together.",
    "Assessment Eligible": "Yes",
    "Curriculum Alignment": "Both",
    "Estimated Time": "35",
    "Voice Script": "Let's solve it together. Start with 2 oranges. Add 2 more oranges. Count all: 4.",
    "Teaching Notes": "Review addition within 10. | Start with 2 oranges. | Add 2 more oranges. | Count all: 4. | Addition means putting groups together.",
    "Required Assets": "visual:orange|type:Multiple Choice",
    "Version Notes": "v1.0 - Mathematics Year 1 Forest complete"
  },
  {
    "Question ID": "FW-Y1-L08-Q012",
    "Status": "Approved",
    "Review Status": "Approved",
    "Subject": "Mathematics",
    "Year": "Year 1",
    "World": "Forest World",
    "Level": "Level 08",
    "Topic": "Review",
    "Subtopic": "Addition review",
    "Learning Objective": "Review addition within 10.",
    "Difficulty": "Easy",
    "Question Type": "Multiple Choice",
    "Question": "3 fish plus 1 more fish. How many fish altogether?",
    "Visual Object": "fish",
    "Visual Description": "Show 3 fish + 1 fish = 4. Use a plus sign, never 'or'.",
    "Options": "3|4|5",
    "Correct Answer": "4",
    "Step 1": "Start with 3 fish.",
    "Step 2": "Add 1 more fish.",
    "Step 3": "Count all: 4.",
    "Final Explanation": "The correct answer is 4.",
    "LearnBot Tip": "Addition means putting groups together.",
    "Assessment Eligible": "Yes",
    "Curriculum Alignment": "Both",
    "Estimated Time": "35",
    "Voice Script": "Let's solve it together. Start with 3 fish. Add 1 more fish. Count all: 4.",
    "Teaching Notes": "Review addition within 10. | Start with 3 fish. | Add 1 more fish. | Count all: 4. | Addition means putting groups together.",
    "Required Assets": "visual:fish|type:Multiple Choice",
    "Version Notes": "v1.0 - Mathematics Year 1 Forest complete"
  },
  {
    "Question ID": "FW-Y1-L08-Q013",
    "Status": "Approved",
    "Review Status": "Approved",
    "Subject": "Mathematics",
    "Year": "Year 1",
    "World": "Forest World",
    "Level": "Level 08",
    "Topic": "Review",
    "Subtopic": "Addition review",
    "Learning Objective": "Review addition within 10.",
    "Difficulty": "Easy",
    "Question Type": "Multiple Choice",
    "Question": "3 flowers plus 2 more flowers. How many flowers altogether?",
    "Visual Object": "flower",
    "Visual Description": "Show 3 flowers + 2 flowers = 5. Use a plus sign, never 'or'.",
    "Options": "4|5|6",
    "Correct Answer": "5",
    "Step 1": "Start with 3 flowers.",
    "Step 2": "Add 2 more flowers.",
    "Step 3": "Count all: 5.",
    "Final Explanation": "The correct answer is 5.",
    "LearnBot Tip": "Addition means putting groups together.",
    "Assessment Eligible": "Yes",
    "Curriculum Alignment": "Both",
    "Estimated Time": "35",
    "Voice Script": "Let's solve it together. Start with 3 flowers. Add 2 more flowers. Count all: 5.",
    "Teaching Notes": "Review addition within 10. | Start with 3 flowers. | Add 2 more flowers. | Count all: 5. | Addition means putting groups together.",
    "Required Assets": "visual:flower|type:Multiple Choice",
    "Version Notes": "v1.0 - Mathematics Year 1 Forest complete"
  },
  {
    "Question ID": "FW-Y1-L08-Q014",
    "Status": "Approved",
    "Review Status": "Approved",
    "Subject": "Mathematics",
    "Year": "Year 1",
    "World": "Forest World",
    "Level": "Level 08",
    "Topic": "Review",
    "Subtopic": "Addition review",
    "Learning Objective": "Review addition within 10.",
    "Difficulty": "Easy",
    "Question Type": "Multiple Choice",
    "Question": "4 ducks plus 1 more ducks. How many ducks altogether?",
    "Visual Object": "duck",
    "Visual Description": "Show 4 ducks + 1 duck = 5. Use a plus sign, never 'or'.",
    "Options": "4|5|6",
    "Correct Answer": "5",
    "Step 1": "Start with 4 ducks.",
    "Step 2": "Add 1 more ducks.",
    "Step 3": "Count all: 5.",
    "Final Explanation": "The correct answer is 5.",
    "LearnBot Tip": "Addition means putting groups together.",
    "Assessment Eligible": "Yes",
    "Curriculum Alignment": "Both",
    "Estimated Time": "35",
    "Voice Script": "Let's solve it together. Start with 4 ducks. Add 1 more ducks. Count all: 5.",
    "Teaching Notes": "Review addition within 10. | Start with 4 ducks. | Add 1 more ducks. | Count all: 5. | Addition means putting groups together.",
    "Required Assets": "visual:duck|type:Multiple Choice",
    "Version Notes": "v1.0 - Mathematics Year 1 Forest complete"
  },
  {
    "Question ID": "FW-Y1-L08-Q015",
    "Status": "Approved",
    "Review Status": "Approved",
    "Subject": "Mathematics",
    "Year": "Year 1",
    "World": "Forest World",
    "Level": "Level 08",
    "Topic": "Review",
    "Subtopic": "Addition review",
    "Learning Objective": "Review addition within 10.",
    "Difficulty": "Easy",
    "Question Type": "Multiple Choice",
    "Question": "4 leaves plus 2 more leaves. How many leaves altogether?",
    "Visual Object": "leaf",
    "Visual Description": "Show 4 leaves + 2 leaves = 6. Use a plus sign, never 'or'.",
    "Options": "5|6|7",
    "Correct Answer": "6",
    "Step 1": "Start with 4 leaves.",
    "Step 2": "Add 2 more leaves.",
    "Step 3": "Count all: 6.",
    "Final Explanation": "The correct answer is 6.",
    "LearnBot Tip": "Addition means putting groups together.",
    "Assessment Eligible": "Yes",
    "Curriculum Alignment": "Both",
    "Estimated Time": "35",
    "Voice Script": "Let's solve it together. Start with 4 leaves. Add 2 more leaves. Count all: 6.",
    "Teaching Notes": "Review addition within 10. | Start with 4 leaves. | Add 2 more leaves. | Count all: 6. | Addition means putting groups together.",
    "Required Assets": "visual:leaf|type:Multiple Choice",
    "Version Notes": "v1.0 - Mathematics Year 1 Forest complete"
  },
  {
    "Question ID": "FW-Y1-L08-Q016",
    "Status": "Approved",
    "Review Status": "Approved",
    "Subject": "Mathematics",
    "Year": "Year 1",
    "World": "Forest World",
    "Level": "Level 08",
    "Topic": "Review",
    "Subtopic": "Addition review",
    "Learning Objective": "Review addition within 10.",
    "Difficulty": "Easy",
    "Question Type": "Multiple Choice",
    "Question": "5 shells plus 1 more shells. How many shells altogether?",
    "Visual Object": "shell",
    "Visual Description": "Show 5 shells + 1 shell = 6. Use a plus sign, never 'or'.",
    "Options": "5|6|7",
    "Correct Answer": "6",
    "Step 1": "Start with 5 shells.",
    "Step 2": "Add 1 more shells.",
    "Step 3": "Count all: 6.",
    "Final Explanation": "The correct answer is 6.",
    "LearnBot Tip": "Addition means putting groups together.",
    "Assessment Eligible": "Yes",
    "Curriculum Alignment": "Both",
    "Estimated Time": "35",
    "Voice Script": "Let's solve it together. Start with 5 shells. Add 1 more shells. Count all: 6.",
    "Teaching Notes": "Review addition within 10. | Start with 5 shells. | Add 1 more shells. | Count all: 6. | Addition means putting groups together.",
    "Required Assets": "visual:shell|type:Multiple Choice",
    "Version Notes": "v1.0 - Mathematics Year 1 Forest complete"
  },
  {
    "Question ID": "FW-Y1-L08-Q017",
    "Status": "Approved",
    "Review Status": "Approved",
    "Subject": "Mathematics",
    "Year": "Year 1",
    "World": "Forest World",
    "Level": "Level 08",
    "Topic": "Review",
    "Subtopic": "Sequence review",
    "Learning Objective": "Review number order within 10.",
    "Difficulty": "Easy",
    "Question Type": "Fill Missing Number",
    "Question": "Fill in the missing number: 1, 2, __, 4.",
    "Visual Object": "number path",
    "Visual Description": "Show forest stepping stones labelled 1, 2, __, 4.",
    "Options": "",
    "Correct Answer": "3",
    "Step 1": "Read the numbers in order.",
    "Step 2": "Count forward to find the blank.",
    "Step 3": "The missing number is 3.",
    "Final Explanation": "The correct answer is 3.",
    "LearnBot Tip": "A blank is like an empty step on the path.",
    "Assessment Eligible": "Yes",
    "Curriculum Alignment": "Both",
    "Estimated Time": "30",
    "Voice Script": "Let's solve it together. Read the numbers in order. Count forward to find the blank. The missing number is 3.",
    "Teaching Notes": "Review number order within 10. | Read the numbers in order. | Count forward to find the blank. | The missing number is 3. | A blank is like an empty step on the path.",
    "Required Assets": "visual:number path|type:Fill Missing Number",
    "Version Notes": "v1.0 - Mathematics Year 1 Forest complete"
  },
  {
    "Question ID": "FW-Y1-L08-Q018",
    "Status": "Approved",
    "Review Status": "Approved",
    "Subject": "Mathematics",
    "Year": "Year 1",
    "World": "Forest World",
    "Level": "Level 08",
    "Topic": "Review",
    "Subtopic": "Sequence review",
    "Learning Objective": "Review number order within 10.",
    "Difficulty": "Easy",
    "Question Type": "Fill Missing Number",
    "Question": "Fill in the missing number: 2, 3, __, 5.",
    "Visual Object": "number path",
    "Visual Description": "Show forest stepping stones labelled 2, 3, __, 5.",
    "Options": "",
    "Correct Answer": "4",
    "Step 1": "Read the numbers in order.",
    "Step 2": "Count forward to find the blank.",
    "Step 3": "The missing number is 4.",
    "Final Explanation": "The correct answer is 4.",
    "LearnBot Tip": "A blank is like an empty step on the path.",
    "Assessment Eligible": "Yes",
    "Curriculum Alignment": "Both",
    "Estimated Time": "30",
    "Voice Script": "Let's solve it together. Read the numbers in order. Count forward to find the blank. The missing number is 4.",
    "Teaching Notes": "Review number order within 10. | Read the numbers in order. | Count forward to find the blank. | The missing number is 4. | A blank is like an empty step on the path.",
    "Required Assets": "visual:number path|type:Fill Missing Number",
    "Version Notes": "v1.0 - Mathematics Year 1 Forest complete"
  },
  {
    "Question ID": "FW-Y1-L08-Q019",
    "Status": "Approved",
    "Review Status": "Approved",
    "Subject": "Mathematics",
    "Year": "Year 1",
    "World": "Forest World",
    "Level": "Level 08",
    "Topic": "Review",
    "Subtopic": "Sequence review",
    "Learning Objective": "Review number order within 10.",
    "Difficulty": "Easy",
    "Question Type": "Fill Missing Number",
    "Question": "Fill in the missing number: 3, 4, __, 6.",
    "Visual Object": "number path",
    "Visual Description": "Show forest stepping stones labelled 3, 4, __, 6.",
    "Options": "",
    "Correct Answer": "5",
    "Step 1": "Read the numbers in order.",
    "Step 2": "Count forward to find the blank.",
    "Step 3": "The missing number is 5.",
    "Final Explanation": "The correct answer is 5.",
    "LearnBot Tip": "A blank is like an empty step on the path.",
    "Assessment Eligible": "Yes",
    "Curriculum Alignment": "Both",
    "Estimated Time": "30",
    "Voice Script": "Let's solve it together. Read the numbers in order. Count forward to find the blank. The missing number is 5.",
    "Teaching Notes": "Review number order within 10. | Read the numbers in order. | Count forward to find the blank. | The missing number is 5. | A blank is like an empty step on the path.",
    "Required Assets": "visual:number path|type:Fill Missing Number",
    "Version Notes": "v1.0 - Mathematics Year 1 Forest complete"
  },
  {
    "Question ID": "FW-Y1-L08-Q020",
    "Status": "Approved",
    "Review Status": "Approved",
    "Subject": "Mathematics",
    "Year": "Year 1",
    "World": "Forest World",
    "Level": "Level 08",
    "Topic": "Review",
    "Subtopic": "Sequence review",
    "Learning Objective": "Review number order within 10.",
    "Difficulty": "Easy",
    "Question Type": "Fill Missing Number",
    "Question": "Fill in the missing number: 4, 5, __, 7.",
    "Visual Object": "number path",
    "Visual Description": "Show forest stepping stones labelled 4, 5, __, 7.",
    "Options": "",
    "Correct Answer": "6",
    "Step 1": "Read the numbers in order.",
    "Step 2": "Count forward to find the blank.",
    "Step 3": "The missing number is 6.",
    "Final Explanation": "The correct answer is 6.",
    "LearnBot Tip": "A blank is like an empty step on the path.",
    "Assessment Eligible": "Yes",
    "Curriculum Alignment": "Both",
    "Estimated Time": "30",
    "Voice Script": "Let's solve it together. Read the numbers in order. Count forward to find the blank. The missing number is 6.",
    "Teaching Notes": "Review number order within 10. | Read the numbers in order. | Count forward to find the blank. | The missing number is 6. | A blank is like an empty step on the path.",
    "Required Assets": "visual:number path|type:Fill Missing Number",
    "Version Notes": "v1.0 - Mathematics Year 1 Forest complete"
  },
  {
    "Question ID": "FW-Y1-L08-Q021",
    "Status": "Approved",
    "Review Status": "Approved",
    "Subject": "Mathematics",
    "Year": "Year 1",
    "World": "Forest World",
    "Level": "Level 08",
    "Topic": "Review",
    "Subtopic": "Sequence review",
    "Learning Objective": "Review number order within 10.",
    "Difficulty": "Easy",
    "Question Type": "Fill Missing Number",
    "Question": "Fill in the missing number: 5, 6, __, 8.",
    "Visual Object": "number path",
    "Visual Description": "Show forest stepping stones labelled 5, 6, __, 8.",
    "Options": "",
    "Correct Answer": "7",
    "Step 1": "Read the numbers in order.",
    "Step 2": "Count forward to find the blank.",
    "Step 3": "The missing number is 7.",
    "Final Explanation": "The correct answer is 7.",
    "LearnBot Tip": "A blank is like an empty step on the path.",
    "Assessment Eligible": "Yes",
    "Curriculum Alignment": "Both",
    "Estimated Time": "30",
    "Voice Script": "Let's solve it together. Read the numbers in order. Count forward to find the blank. The missing number is 7.",
    "Teaching Notes": "Review number order within 10. | Read the numbers in order. | Count forward to find the blank. | The missing number is 7. | A blank is like an empty step on the path.",
    "Required Assets": "visual:number path|type:Fill Missing Number",
    "Version Notes": "v1.0 - Mathematics Year 1 Forest complete"
  },
  {
    "Question ID": "FW-Y1-L08-Q022",
    "Status": "Approved",
    "Review Status": "Approved",
    "Subject": "Mathematics",
    "Year": "Year 1",
    "World": "Forest World",
    "Level": "Level 08",
    "Topic": "Review",
    "Subtopic": "Sequence review",
    "Learning Objective": "Review number order within 10.",
    "Difficulty": "Easy",
    "Question Type": "Fill Missing Number",
    "Question": "Fill in the missing number: 6, 7, __, 9.",
    "Visual Object": "number path",
    "Visual Description": "Show forest stepping stones labelled 6, 7, __, 9.",
    "Options": "",
    "Correct Answer": "8",
    "Step 1": "Read the numbers in order.",
    "Step 2": "Count forward to find the blank.",
    "Step 3": "The missing number is 8.",
    "Final Explanation": "The correct answer is 8.",
    "LearnBot Tip": "A blank is like an empty step on the path.",
    "Assessment Eligible": "Yes",
    "Curriculum Alignment": "Both",
    "Estimated Time": "30",
    "Voice Script": "Let's solve it together. Read the numbers in order. Count forward to find the blank. The missing number is 8.",
    "Teaching Notes": "Review number order within 10. | Read the numbers in order. | Count forward to find the blank. | The missing number is 8. | A blank is like an empty step on the path.",
    "Required Assets": "visual:number path|type:Fill Missing Number",
    "Version Notes": "v1.0 - Mathematics Year 1 Forest complete"
  },
  {
    "Question ID": "FW-Y1-L08-Q023",
    "Status": "Approved",
    "Review Status": "Approved",
    "Subject": "Mathematics",
    "Year": "Year 1",
    "World": "Forest World",
    "Level": "Level 08",
    "Topic": "Review",
    "Subtopic": "Sequence review",
    "Learning Objective": "Review number order within 10.",
    "Difficulty": "Easy",
    "Question Type": "Fill Missing Number",
    "Question": "Fill in the missing number: 7, 8, __, 10.",
    "Visual Object": "number path",
    "Visual Description": "Show forest stepping stones labelled 7, 8, __, 10.",
    "Options": "",
    "Correct Answer": "9",
    "Step 1": "Read the numbers in order.",
    "Step 2": "Count forward to find the blank.",
    "Step 3": "The missing number is 9.",
    "Final Explanation": "The correct answer is 9.",
    "LearnBot Tip": "A blank is like an empty step on the path.",
    "Assessment Eligible": "Yes",
    "Curriculum Alignment": "Both",
    "Estimated Time": "30",
    "Voice Script": "Let's solve it together. Read the numbers in order. Count forward to find the blank. The missing number is 9.",
    "Teaching Notes": "Review number order within 10. | Read the numbers in order. | Count forward to find the blank. | The missing number is 9. | A blank is like an empty step on the path.",
    "Required Assets": "visual:number path|type:Fill Missing Number",
    "Version Notes": "v1.0 - Mathematics Year 1 Forest complete"
  },
  {
    "Question ID": "FW-Y1-L08-Q024",
    "Status": "Approved",
    "Review Status": "Approved",
    "Subject": "Mathematics",
    "Year": "Year 1",
    "World": "Forest World",
    "Level": "Level 08",
    "Topic": "Review",
    "Subtopic": "Comparison review",
    "Learning Objective": "Review comparing groups.",
    "Difficulty": "Easy",
    "Question Type": "Tap Correct Group",
    "Question": "Tap the group with more apples.",
    "Visual Object": "apple",
    "Visual Description": "Show Group A with 3 apples and Group B with 5 apples. Use labels.",
    "Options": "Group A: 3 apples|Group B: 5 apples",
    "Correct Answer": "Group B",
    "Step 1": "Count Group A.",
    "Step 2": "Count Group B.",
    "Step 3": "Compare the two totals.",
    "Final Explanation": "The correct answer is Group B.",
    "LearnBot Tip": "Compare by counting both groups first.",
    "Assessment Eligible": "Yes",
    "Curriculum Alignment": "Both",
    "Estimated Time": "35",
    "Voice Script": "Let's solve it together. Count Group A. Count Group B. Compare the two totals.",
    "Teaching Notes": "Review comparing groups. | Count Group A. | Count Group B. | Compare the two totals. | Compare by counting both groups first.",
    "Required Assets": "visual:apple|type:Tap Correct Group",
    "Version Notes": "v1.0 - Mathematics Year 1 Forest complete"
  },
  {
    "Question ID": "FW-Y1-L08-Q025",
    "Status": "Approved",
    "Review Status": "Approved",
    "Subject": "Mathematics",
    "Year": "Year 1",
    "World": "Forest World",
    "Level": "Level 08",
    "Topic": "Review",
    "Subtopic": "Comparison review",
    "Learning Objective": "Review comparing groups.",
    "Difficulty": "Easy",
    "Question Type": "Tap Correct Group",
    "Question": "Tap the group with fewer stars.",
    "Visual Object": "star",
    "Visual Description": "Show Group A with 6 stars and Group B with 2 stars. Use labels.",
    "Options": "Group A: 6 stars|Group B: 2 stars",
    "Correct Answer": "Group B",
    "Step 1": "Count Group A.",
    "Step 2": "Count Group B.",
    "Step 3": "Compare the two totals.",
    "Final Explanation": "The correct answer is Group B.",
    "LearnBot Tip": "Compare by counting both groups first.",
    "Assessment Eligible": "Yes",
    "Curriculum Alignment": "Both",
    "Estimated Time": "35",
    "Voice Script": "Let's solve it together. Count Group A. Count Group B. Compare the two totals.",
    "Teaching Notes": "Review comparing groups. | Count Group A. | Count Group B. | Compare the two totals. | Compare by counting both groups first.",
    "Required Assets": "visual:star|type:Tap Correct Group",
    "Version Notes": "v1.0 - Mathematics Year 1 Forest complete"
  },
  {
    "Question ID": "FW-Y1-L08-Q026",
    "Status": "Approved",
    "Review Status": "Approved",
    "Subject": "Mathematics",
    "Year": "Year 1",
    "World": "Forest World",
    "Level": "Level 08",
    "Topic": "Review",
    "Subtopic": "Comparison review",
    "Learning Objective": "Review comparing groups.",
    "Difficulty": "Easy",
    "Question Type": "Tap Correct Group",
    "Question": "Tap the groups with the same number of ducks.",
    "Visual Object": "duck",
    "Visual Description": "Show Group A with 4 ducks and 4 ducks and Group B with 4 ducks and 3 ducks. Use labels.",
    "Options": "Group A: 4 ducks and 4 ducks|Group B: 4 ducks and 3 ducks",
    "Correct Answer": "Group A",
    "Step 1": "Count Group A.",
    "Step 2": "Count Group B.",
    "Step 3": "Compare the two totals.",
    "Final Explanation": "The correct answer is Both.",
    "LearnBot Tip": "Compare by counting both groups first.",
    "Assessment Eligible": "Yes",
    "Curriculum Alignment": "Both",
    "Estimated Time": "35",
    "Voice Script": "Let's solve it together. Count Group A. Count Group B. Compare the two totals.",
    "Teaching Notes": "Review comparing groups. | Count Group A. | Count Group B. | Compare the two totals. | Compare by counting both groups first.",
    "Required Assets": "visual:duck|type:Tap Correct Group",
    "Version Notes": "v1.0 - Mathematics Year 1 Forest complete"
  },
  {
    "Question ID": "FW-Y1-L08-Q027",
    "Status": "Approved",
    "Review Status": "Approved",
    "Subject": "Mathematics",
    "Year": "Year 1",
    "World": "Forest World",
    "Level": "Level 08",
    "Topic": "Review",
    "Subtopic": "Comparison review",
    "Learning Objective": "Review comparing groups.",
    "Difficulty": "Medium",
    "Question Type": "Tap Correct Group",
    "Question": "Tap the group with more flowers.",
    "Visual Object": "flower",
    "Visual Description": "Show Group A with 7 flowers and Group B with 9 flowers. Use labels.",
    "Options": "Group A: 7 flowers|Group B: 9 flowers",
    "Correct Answer": "Group B",
    "Step 1": "Count Group A.",
    "Step 2": "Count Group B.",
    "Step 3": "Compare the two totals.",
    "Final Explanation": "The correct answer is Group B.",
    "LearnBot Tip": "Compare by counting both groups first.",
    "Assessment Eligible": "Yes",
    "Curriculum Alignment": "Both",
    "Estimated Time": "35",
    "Voice Script": "Let's solve it together. Count Group A. Count Group B. Compare the two totals.",
    "Teaching Notes": "Review comparing groups. | Count Group A. | Count Group B. | Compare the two totals. | Compare by counting both groups first.",
    "Required Assets": "visual:flower|type:Tap Correct Group",
    "Version Notes": "v1.0 - Mathematics Year 1 Forest complete"
  },
  {
    "Question ID": "FW-Y1-L08-Q028",
    "Status": "Approved",
    "Review Status": "Approved",
    "Subject": "Mathematics",
    "Year": "Year 1",
    "World": "Forest World",
    "Level": "Level 08",
    "Topic": "Review",
    "Subtopic": "Comparison review",
    "Learning Objective": "Review comparing groups.",
    "Difficulty": "Medium",
    "Question Type": "Tap Correct Group",
    "Question": "Tap the group with fewer fish.",
    "Visual Object": "fish",
    "Visual Description": "Show Group A with 8 fish and Group B with 5 fish. Use labels.",
    "Options": "Group A: 8 fish|Group B: 5 fish",
    "Correct Answer": "Group B",
    "Step 1": "Count Group A.",
    "Step 2": "Count Group B.",
    "Step 3": "Compare the two totals.",
    "Final Explanation": "The correct answer is Group B.",
    "LearnBot Tip": "Compare by counting both groups first.",
    "Assessment Eligible": "Yes",
    "Curriculum Alignment": "Both",
    "Estimated Time": "35",
    "Voice Script": "Let's solve it together. Count Group A. Count Group B. Compare the two totals.",
    "Teaching Notes": "Review comparing groups. | Count Group A. | Count Group B. | Compare the two totals. | Compare by counting both groups first.",
    "Required Assets": "visual:fish|type:Tap Correct Group",
    "Version Notes": "v1.0 - Mathematics Year 1 Forest complete"
  },
  {
    "Question ID": "FW-Y1-L08-Q029",
    "Status": "Approved",
    "Review Status": "Approved",
    "Subject": "Mathematics",
    "Year": "Year 1",
    "World": "Forest World",
    "Level": "Level 08",
    "Topic": "Review",
    "Subtopic": "Comparison review",
    "Learning Objective": "Review comparing groups.",
    "Difficulty": "Medium",
    "Question Type": "Tap Correct Group",
    "Question": "Tap the group with more leaves.",
    "Visual Object": "leaf",
    "Visual Description": "Show Group A with 10 leaves and Group B with 6 leaves. Use labels.",
    "Options": "Group A: 10 leaves|Group B: 6 leaves",
    "Correct Answer": "Group A",
    "Step 1": "Count Group A.",
    "Step 2": "Count Group B.",
    "Step 3": "Compare the two totals.",
    "Final Explanation": "The correct answer is Group A.",
    "LearnBot Tip": "Compare by counting both groups first.",
    "Assessment Eligible": "Yes",
    "Curriculum Alignment": "Both",
    "Estimated Time": "35",
    "Voice Script": "Let's solve it together. Count Group A. Count Group B. Compare the two totals.",
    "Teaching Notes": "Review comparing groups. | Count Group A. | Count Group B. | Compare the two totals. | Compare by counting both groups first.",
    "Required Assets": "visual:leaf|type:Tap Correct Group",
    "Version Notes": "v1.0 - Mathematics Year 1 Forest complete"
  },
  {
    "Question ID": "FW-Y1-L08-Q030",
    "Status": "Approved",
    "Review Status": "Approved",
    "Subject": "Mathematics",
    "Year": "Year 1",
    "World": "Forest World",
    "Level": "Level 08",
    "Topic": "Review",
    "Subtopic": "Comparison review",
    "Learning Objective": "Review comparing groups.",
    "Difficulty": "Easy",
    "Question Type": "Tap Correct Group",
    "Question": "Tap the group with fewer shells.",
    "Visual Object": "shell",
    "Visual Description": "Show Group A with 1 shell and Group B with 3 shells. Use labels.",
    "Options": "Group A: 1 shell|Group B: 3 shells",
    "Correct Answer": "Group A",
    "Step 1": "Count Group A.",
    "Step 2": "Count Group B.",
    "Step 3": "Compare the two totals.",
    "Final Explanation": "The correct answer is Group A.",
    "LearnBot Tip": "Compare by counting both groups first.",
    "Assessment Eligible": "Yes",
    "Curriculum Alignment": "Both",
    "Estimated Time": "35",
    "Voice Script": "Let's solve it together. Count Group A. Count Group B. Compare the two totals.",
    "Teaching Notes": "Review comparing groups. | Count Group A. | Count Group B. | Compare the two totals. | Compare by counting both groups first.",
    "Required Assets": "visual:shell|type:Tap Correct Group",
    "Version Notes": "v1.0 - Mathematics Year 1 Forest complete"
  }
]
